kameris_formats/__init__.py
kameris_formats/_common.py
kameris_formats/dist_reader.py
kameris_formats/dist_writer.py
kameris_formats/repr_reader.py
kameris_formats/repr_writer.py
kameris_formats-1.0.6.dist-info/METADATA
kameris_formats-1.0.6.dist-info/WHEEL
kameris_formats-1.0.6.dist-info/top_level.txt
kameris_formats-1.0.6.dist-info/RECORD
