Metadata-Version: 2.1
Name: kameris-formats
Version: 1.0.6
Summary: Reader and writer implementations for the file formats used by kameris-backend.
Home-page: https://github.com/stephensolis/kameris-formats/
Author: Stephen
Author-email: stephsolis@gmail.com
License: MIT
Platform: UNKNOWN
Classifier: Development Status :: 4 - Beta
Classifier: License :: OSI Approved :: MIT License
Classifier: Programming Language :: Python :: 2
Classifier: Programming Language :: Python :: 2.7
Classifier: Programming Language :: Python :: 3
Classifier: Programming Language :: Python :: 3.4
Classifier: Programming Language :: Python :: 3.5
Classifier: Programming Language :: Python :: 3.6
Classifier: Topic :: Scientific/Engineering
Requires-Dist: numpy
Requires-Dist: scipy
